{
	"name": "PL_Stg_Competitor_Product_Master_IN1675_copy1",
	"properties": {
		"activities": [
			{
				"name": "CP_STG_Competitor_Product_Master_AzureSQL",
				"type": "Copy",
				"dependsOn": [],
				"policy": {
					"timeout": "0.12:00:00",
					"retry": 0,
					"retryIntervalInSeconds": 30,
					"secureOutput": false,
					"secureInput": false
				},
				"userProperties": [],
				"typeProperties": {
					"source": {
						"type": "AzureSqlSource",
						"additionalColumns": [
							{
								"name": "CreatedBy",
								"value": {
									"value": "@pipeline().Pipeline",
									"type": "Expression"
								}
							},
							{
								"name": "CreatedDate",
								"value": {
									"value": "@utcNow()",
									"type": "Expression"
								}
							},
							{
								"name": "UpdatedBy",
								"value": {
									"value": "UNK\n",
									"type": "Expression"
								}
							},
							{
								"name": "UpdatedDate",
								"value": {
									"value": "1900-01-01 00:00:00",
									"type": "Expression"
								}
							}
						],
						"queryTimeout": "02:00:00",
						"partitionOption": "None"
					},
					"sink": {
						"type": "AzureSqlSink",
						"preCopyScript": "Truncate Table Stg_Competitor_Product_Master_IN1675",
						"writeBehavior": "insert",
						"sqlWriterUseTableLock": false,
						"disableMetricsCollection": false
					},
					"enableStaging": false,
					"translator": {
						"type": "TabularTranslator",
						"mappings": [
							{
								"source": {
									"name": "SKUCode",
									"type": "Double",
									"physicalType": "float"
								},
								"sink": {
									"name": "SKUCode",
									"type": "Int32",
									"physicalType": "int"
								}
							},
							{
								"source": {
									"name": "ItemName",
									"type": "String",
									"physicalType": "nvarchar"
								},
								"sink": {
									"name": "ItemName",
									"type": "String",
									"physicalType": "varchar"
								}
							},
							{
								"source": {
									"name": "CompanyCode",
									"type": "String",
									"physicalType": "nvarchar"
								},
								"sink": {
									"name": "CompanyCode",
									"type": "String",
									"physicalType": "varchar"
								}
							},
							{
								"source": {
									"name": "IndustryName",
									"type": "String",
									"physicalType": "nvarchar"
								},
								"sink": {
									"name": "IndustryName",
									"type": "String",
									"physicalType": "varchar"
								}
							},
							{
								"source": {
									"name": "BrandFamily",
									"type": "String",
									"physicalType": "nvarchar"
								},
								"sink": {
									"name": "BrandFamily",
									"type": "String",
									"physicalType": "varchar"
								}
							},
							{
								"source": {
									"name": "BrandCode",
									"type": "String",
									"physicalType": "nvarchar"
								},
								"sink": {
									"name": "BrandCode",
									"type": "String",
									"physicalType": "varchar"
								}
							},
							{
								"source": {
									"name": "BrandName",
									"type": "String",
									"physicalType": "nvarchar"
								},
								"sink": {
									"name": "BrandName",
									"type": "String",
									"physicalType": "varchar"
								}
							},
							{
								"source": {
									"name": "ReportingSegment",
									"type": "String",
									"physicalType": "nvarchar"
								},
								"sink": {
									"name": "ReportingSegment",
									"type": "String",
									"physicalType": "varchar"
								}
							},
							{
								"source": {
									"name": "BrandPackSize",
									"type": "String",
									"physicalType": "nvarchar"
								},
								"sink": {
									"name": "BrandPackSize",
									"type": "String",
									"physicalType": "varchar"
								}
							},
							{
								"source": {
									"name": "PackTypeCode",
									"type": "String",
									"physicalType": "nvarchar"
								},
								"sink": {
									"name": "PackTypeCode",
									"type": "String",
									"physicalType": "varchar"
								}
							},
							{
								"source": {
									"name": "BrandPackType",
									"type": "String",
									"physicalType": "nvarchar"
								},
								"sink": {
									"name": "BrandPackType",
									"type": "String",
									"physicalType": "varchar"
								}
							},
							{
								"source": {
									"name": "State Code",
									"type": "String",
									"physicalType": "nvarchar"
								},
								"sink": {
									"name": "StateCode",
									"type": "String",
									"physicalType": "varchar"
								}
							},
							{
								"source": {
									"name": "State",
									"type": "String",
									"physicalType": "nvarchar"
								},
								"sink": {
									"name": "State",
									"type": "String",
									"physicalType": "varchar"
								}
							},
							{
								"source": {
									"name": "ProductCategory",
									"type": "String",
									"physicalType": "nvarchar"
								},
								"sink": {
									"name": "ProductCategory",
									"type": "String",
									"physicalType": "varchar"
								}
							},
							{
								"source": {
									"name": "ProductSegment",
									"type": "String",
									"physicalType": "nvarchar"
								},
								"sink": {
									"name": "ProductSegment",
									"type": "String",
									"physicalType": "varchar"
								}
							},
							{
								"source": {
									"name": "Flavour",
									"type": "String",
									"physicalType": "nvarchar"
								},
								"sink": {
									"name": "Flavour",
									"type": "String",
									"physicalType": "varchar"
								}
							},
							{
								"source": {
									"name": "SubFlavour",
									"type": "String",
									"physicalType": "nvarchar"
								},
								"sink": {
									"name": "SubFlavour",
									"type": "String",
									"physicalType": "varchar"
								}
							},
							{
								"source": {
									"name": "Division",
									"type": "String",
									"physicalType": "nvarchar"
								},
								"sink": {
									"name": "Division",
									"type": "String",
									"physicalType": "varchar"
								}
							},
							{
								"source": {
									"name": "CreatedBy",
									"type": "String"
								},
								"sink": {
									"name": "CreatedBy",
									"type": "String",
									"physicalType": "varchar"
								}
							},
							{
								"source": {
									"name": "CreatedDate",
									"type": "String"
								},
								"sink": {
									"name": "CreatedDate",
									"type": "DateTime",
									"physicalType": "datetime"
								}
							},
							{
								"source": {
									"name": "UpdatedBy",
									"type": "String"
								},
								"sink": {
									"name": "UpdatedBy",
									"type": "String",
									"physicalType": "varchar"
								}
							},
							{
								"source": {
									"name": "UpdatedDate",
									"type": "String"
								},
								"sink": {
									"name": "UpdatedDate",
									"type": "DateTime",
									"physicalType": "datetime"
								}
							}
						],
						"typeConversion": true,
						"typeConversionSettings": {
							"allowDataTruncation": true,
							"treatBooleanAsNumber": false
						}
					}
				},
				"inputs": [
					{
						"referenceName": "DS_Azure_SQL_IN1675",
						"type": "DatasetReference",
						"parameters": {
							"SchemaName": "Alcobev",
							"TableName": "CompetitorProductMaster",
							"DatabaseName": "Trainer"
						}
					}
				],
				"outputs": [
					{
						"referenceName": "DS_Azure_SQL_IN1675",
						"type": "DatasetReference",
						"parameters": {
							"SchemaName": "DMuthuku",
							"TableName": "Stg_Competitor_Product_Master_IN1675",
							"DatabaseName": "Target_ADF_B2025"
						}
					}
				]
			}
		],
		"folder": {
			"name": "PL_Stg_Tgt/PL_Src_Stg"
		},
		"annotations": []
	}
}